tat/__init__.py
tat/__main__.py
tat/checkable_image_entry.py
tat/cluster_editor.py
tat/cluster_image_entry.py
tat/clustering.py
tat/image_entry.py
tat/layer_data.py
tat/layer_image_entry.py
tat/main_window.py
tat/preview_window.py
tat/progress_window.py
tat/ui_editor_window.py
tat/ui_main_window.py
tat/ui_progress_bar.py
tat/utils.py
tat/gui/__init__.py
tat/gui/main.py
tat-1.1.1.dist-info/AUTHORS
tat-1.1.1.dist-info/LICENSE
tat-1.1.1.dist-info/METADATA
tat-1.1.1.dist-info/WHEEL
tat-1.1.1.dist-info/entry_points.txt
tat-1.1.1.dist-info/pbr.json
tat-1.1.1.dist-info/top_level.txt
tat-1.1.1.dist-info/RECORD
